martens/__init__.py
martens/martens.py
martens-0.4.25.dist-info/licenses/AUTHORS.rst
martens-0.4.25.dist-info/licenses/LICENSE
martens-0.4.25.dist-info/METADATA
martens-0.4.25.dist-info/WHEEL
martens-0.4.25.dist-info/top_level.txt
martens-0.4.25.dist-info/RECORD
