Metadata-Version: 2.4
Name: martens
Version: 0.4.25
Summary: Succinct small scale data manipulation
Home-page: https://github.com/arowley-ai/martens
Author: Alex Rowley
Author-email: 
License: MIT license
Keywords: martens
Classifier: Development Status :: 2 - Pre-Alpha
Classifier: Intended Audience :: Developers
Classifier: License :: OSI Approved :: MIT License
Classifier: Natural Language :: English
Classifier: Programming Language :: Python :: 3
Classifier: Programming Language :: Python :: 3.6
Classifier: Programming Language :: Python :: 3.7
Classifier: Programming Language :: Python :: 3.8
Requires-Python: >=3.8
License-File: LICENSE
License-File: AUTHORS.rst
Requires-Dist: openpyxl~=3.1.2
Requires-Dist: xlrd~=2.0.1
Requires-Dist: setuptools>=69.1.0
Dynamic: author
Dynamic: classifier
Dynamic: description
Dynamic: home-page
Dynamic: keywords
Dynamic: license
Dynamic: license-file
Dynamic: requires-dist
Dynamic: requires-python
Dynamic: summary
